[
  {
    "key": "ctrl-h",
    "command": "workbench.action.navigateLeft",
    "when": "vim.mode == 'Normal' && (editorTextFocus || !inputFocus)"
  },
  {
    "key": "ctrl-l",
    "command": "workbench.action.navigateRight",
    "when": "vim.mode == 'Normal' && (editorTextFocus || !inputFocus)"
  },
  {
    "key": "ctrl-k",
    "command": "workbench.action.navigateUp"
  },
  {
    "key": "ctrl-j",
    "command": "workbench.action.navigateDown"
  },
  {
    "key": "; l",
    "command": "workbench.action.showAllEditors",
    "when": "vim.mode == 'Normal' && (editorTextFocus || !inputFocus)"
  },
  {
    "key": "space a",
    "command": "workbench.action.toggleSidebarVisibility",
    "when": "vim.mode == 'Normal' && (editorTextFocus || !inputFocus)"
  },
  {
    "key": "shift-l",
    "command": "workbench.action.nextEditorInGroup",
    "when": "(vim.mode == 'Normal' ||  vim.mode == 'Visual') && (editorTextFocus || !inputFocus)"
  },
  {
    "key": "shift-h",
    "command": "workbench.action.previousEditorInGroup",
    "when": "(vim.mode == 'Normal' ||  vim.mode == 'Visual') && (editorTextFocus || !inputFocus)"
  },
  {
    "key": "space b d",
    "command": "workbench.action.closeActiveEditor",
    "when": "vim.mode == 'Normal' && editorTextFocus"
  },
  {
    "key": "space f f",
    "command": "workbench.action.quickOpen",
    "when": "vim.mode == 'Normal' && (editorTextFocus || !inputFocus)"
  },
  {
    "key": "space f g",
    "command": "workbench.action.findInFiles",
    "when": "vim.mode == 'Normal' && (editorTextFocus || !inputFocus)"
  },
  {
    "key": "space g g",
    "command": "runCommands",
    "when": "vim.mode == 'Normal' && (editorTextFocus || !inputFocus)",
    "args": {
      "commands": ["workbench.view.scm", "workbench.scm.focus"]
    }
  },
  {
    "key": "space s v",
    "command": "workbench.action.splitEditor",
    "when": "vim.mode == 'Normal' && (editorTextFocus || !inputFocus)"
  },
  {
    "key": "space s s",
    "command": "workbench.action.splitEditorDown",
    "when": "vim.mode == 'Normal' && (editorTextFocus || !inputFocus)"
  },
  {
    "key": "-",
    "command": "workbench.view.explorer",
    "when": "vim.mode == 'Normal' && (editorTextFocus || !inputFocus)"
  },

  // Coding
  {
    "key": "shift-j",
    "command": "editor.action.moveLinesDownAction",
    "when": "vim.mode != 'Insert' && editorTextFocus"
  },
  {
    "key": "shift-k",
    "command": "editor.action.moveLinesUpAction",
    "when": "vim.mode != 'Insert' && editorTextFocus"
  },
  {
    "key": "shift-k",
    "command": "editor.action.showHover",
    "when": "vim.mode == 'Normal' && editorTextFocus"
  },
  {
    "key": "space f a",
    "command": "editor.action.formatDocument",
    "when": "vim.mode == 'Normal' && editorTextFocus"
  },
  {
    "key": "c a",
    "command": "editor.action.codeAction",
    "when": "vim.mode == 'Normal' && editorTextFocus"
  },
  {
    "key": "r n",
    "command": "editor.action.rename",
    "when": "vim.mode == 'Normal' && editorTextFocus"
  },
  {
    "key": "g d",
    "command": "editor.action.revealDefinition",
    "when": "vim.mode == 'Normal' && editorTextFocus"
  },
  {
    "key": "g r",
    "command": "editor.action.goToReferences",
    "when": "vim.mode == 'Normal' && editorTextFocus"
  },
  {
    "key": "ctrl-n",
    "command": "editor.action.addSelectionToNextFindMatch",
    "when": "(vim.mode == 'Normal' || vim.mode == 'Visual') && (editorTextFocus || !inputFocus)"
  },

  // File explorer
  {
    "key": "c i w",
    "command": "renameFile",
    "when": "filesExplorerFocus && foldersViewVisibile && !explorerResourceIsRoot && !explorerResourceReadonly && !inputFocus"
  },
  {
    "key": "y y",
    "command": "filesExplorer.copy",
    "when": "filesExplorerFocus && foldersViewVisibile && !explorerResourceIsRoot && !explorerResourceReadonly && !inputFocus"
  },
  {
    "key": "p",
    "command": "filesExplorer.paste",
    "when": "filesExplorerFocus && foldersViewVisibile && !explorerResourceIsRoot && !explorerResourceReadonly && !inputFocus"
  },
  {
    "key": "x",
    "command": "filesExplorer.cut",
    "when": "filesExplorerFocus && foldersViewVisibile && !explorerResourceIsRoot && !explorerResourceReadonly && !inputFocus"
  },
  {
    "key": "a",
    "command": "explorer.newFile",
    "when": "filesExplorerFocus && foldersViewVisibile && !explorerResourceIsRoot && !explorerResourceReadonly && !inputFocus"
  },
  {
    "key": "shift-a",
    "command": "explorer.newFolder",
    "when": "filesExplorerFocus && foldersViewVisibile && !explorerResourceIsRoot && !explorerResourceReadonly && !inputFocus"
  },
  {
    "key": "ctrl-h",
    "command": "explorer.openToSide",
    "when": "filesExplorerFocus && foldersViewVisibile && !explorerResourceIsRoot && !explorerResourceReadonly && !inputFocus"
  },
  {
    "key": "ctrl-s",
    "command": "runCommands",
    "when": "filesExplorerFocus && foldersViewVisibile && !explorerResourceIsRoot && !explorerResourceReadonly && !inputFocus",
    "args": {
      "commands": [
        "workbench.action.splitEditorDown",
        "explorer.openAndPassFocus",
        "workbench.action.closeOtherEditors"
      ]
    }
  },
  {
    "key": "enter",
    "command": "explorer.openAndPassFocus",
    "when": "filesExplorerFocus && foldersViewVisibile && !explorerResourceIsRoot && !explorerResourceReadonly && !inputFocus"
  },
  {
    "key": "enter",
    "command": "-renameFile",
    "when": "filesExplorerFocus && foldersViewVisible && !explorerResourceIsRoot && !explorerResourceReadonly && !inputFocus"
  },
  {
    "key": "cmd+i",
    "command": "composerMode.agent"
  }
]
